pychromedriver/__init__.py
pychromedriver/chromedriver-linux64/LICENSE.chromedriver
pychromedriver/chromedriver-linux64/chromedriver
pychromedriver/chromedriver-mac-arm64/LICENSE.chromedriver
pychromedriver/chromedriver-mac-arm64/chromedriver
pychromedriver/chromedriver-mac-x64/LICENSE.chromedriver
pychromedriver/chromedriver-mac-x64/chromedriver
pychromedriver/chromedriver-win32/LICENSE.chromedriver
pychromedriver/chromedriver-win32/chromedriver.exe
pychromedriver/chromedriver-win64/LICENSE.chromedriver
pychromedriver/chromedriver-win64/chromedriver.exe
pychromedriver-121.0.dist-info/LICENSE
pychromedriver-121.0.dist-info/METADATA
pychromedriver-121.0.dist-info/WHEEL
pychromedriver-121.0.dist-info/top_level.txt
pychromedriver-121.0.dist-info/RECORD
