Metadata-Version: 2.1
Name: pychromedriver
Version: 121.0
Summary: A package to sync chrome driver to lastest version
Home-page: https://github.com/parklam/pychromedriver
Author: Park Lam
Author-email: lqmonline@gmail.com
Keywords: chromedriver chrome driver
Classifier: Programming Language :: Python :: 3
Classifier: License :: OSI Approved :: Apache Software License
Classifier: Operating System :: OS Independent
License-File: LICENSE
